iso_container/__init__.py
iso_container/datasets.json
iso_container/iso_container.py
iso_container-1.0.3.dist-info/LICENSE
iso_container-1.0.3.dist-info/METADATA
iso_container-1.0.3.dist-info/WHEEL
iso_container-1.0.3.dist-info/top_level.txt
iso_container-1.0.3.dist-info/RECORD
