Metadata-Version: 2.1
Name: iso-container
Version: 1.0.3
Summary: A Python package for ISO 6346 container information and validation.
Home-page: https://github.com/Jiseoup/iso-container
Author: Jiseoup
Author-email: jseoup@gmail.com
License: MIT
Keywords: container,iso container,container validate,iso,iso6346
Classifier: Development Status :: 5 - Production/Stable
Classifier: Intended Audience :: Developers
Classifier: Programming Language :: Python :: 3
Classifier: Operating System :: OS Independent
Classifier: License :: OSI Approved :: MIT License
Requires-Python: >=3.7
License-File: LICENSE
